MANIFEST.in
requirements.txt
setup.py
kccommons/__init__.py
kccommons/codingutlis.py
kccommons/configutlis.py
kccommons/constutlis.py
kccommons/datetimeutlis.py
kccommons/dirutlis.py
kccommons/exceptionutlis.py
kccommons/fileutlis.py
kccommons/javautlis.py
kccommons/logutlis.py
kccommons/osutlis.py
kccommons/pathutlis.py
kccommons.egg-info/PKG-INFO
kccommons.egg-info/SOURCES.txt
kccommons.egg-info/dependency_links.txt
kccommons.egg-info/requires.txt
kccommons.egg-info/top_level.txt