Metadata-Version: 1.2
Name: kccommons
Version: 1.0.1
Summary: 常用工具包
Home-page: UNKNOWN
Author: LiYanAn
Author-email: liyanan2010@sina.cn
License: UNKNOWN
Platform: UNKNOWN
Requires-Python: >=3.7.0
